requirements.txt
pytigon_lib/__init__.py
pytigon_lib/schandroid/__init__.py
pytigon_lib/schandroid/android_client.py
pytigon_lib/schdjangoext/__init__.py
pytigon_lib/schdjangoext/allauth.py
pytigon_lib/schdjangoext/django_ihtml.py
pytigon_lib/schdjangoext/django_init.py
pytigon_lib/schdjangoext/django_manage.py
pytigon_lib/schdjangoext/django_settings.py
pytigon_lib/schdjangoext/email.py
pytigon_lib/schdjangoext/fastform.py
pytigon_lib/schdjangoext/fields.py
pytigon_lib/schdjangoext/formfields.py
pytigon_lib/schdjangoext/formwidgets.py
pytigon_lib/schdjangoext/graphql.py
pytigon_lib/schdjangoext/import_from_db.py
pytigon_lib/schdjangoext/models.py
pytigon_lib/schdjangoext/oauth_for_graphql.py
pytigon_lib/schdjangoext/python_style_template_loader.py
pytigon_lib/schdjangoext/render.py
pytigon_lib/schdjangoext/rest_tools.py
pytigon_lib/schdjangoext/server.py
pytigon_lib/schdjangoext/spreadsheet_render.py
pytigon_lib/schdjangoext/tools.py
pytigon_lib/schdjangoext/widgets.py
pytigon_lib/schfs/__init__.py
pytigon_lib/schfs/tasks.py
pytigon_lib/schfs/vfstools.py
pytigon_lib/schhtml/__init__.py
pytigon_lib/schhtml/atom.py
pytigon_lib/schhtml/basedc.py
pytigon_lib/schhtml/basehtmltags.py
pytigon_lib/schhtml/cairodc.py
pytigon_lib/schhtml/css.py
pytigon_lib/schhtml/docxdc.py
pytigon_lib/schhtml/html_tags.py
pytigon_lib/schhtml/htmltools.py
pytigon_lib/schhtml/htmlviewer.py
pytigon_lib/schhtml/main.py
pytigon_lib/schhtml/pdfdc.py
pytigon_lib/schhtml/render_helpers.py
pytigon_lib/schhtml/wxdc.py
pytigon_lib/schhtml/wxgc.py
pytigon_lib/schhtml/xlsxdc.py
pytigon_lib/schhtml/icss/wiki.icss
pytigon_lib/schhtml/tags/__init__.py
pytigon_lib/schhtml/tags/atom_tags.py
pytigon_lib/schhtml/tags/block_tags.py
pytigon_lib/schhtml/tags/css_tags.py
pytigon_lib/schhtml/tags/extra_tags.py
pytigon_lib/schhtml/tags/p_tags.py
pytigon_lib/schhtml/tags/page_tags.py
pytigon_lib/schhtml/tags/table_tags.py
pytigon_lib/schhttptools/__init__.py
pytigon_lib/schhttptools/asgi_bridge.py
pytigon_lib-0.250514.dist-info/licenses/LICENSE
pytigon_lib-0.250514.dist-info/METADATA
pytigon_lib-0.250514.dist-info/WHEEL
pytigon_lib-0.250514.dist-info/top_level.txt
pytigon_lib-0.250514.dist-info/RECORD
