Metadata-Version: 2.4
Name: pytigon-lib
Version: 0.250514
Summary: Pytigon library
Author: Sławomir Chołaj
Author-email: slawomir.cholaj@gmail.com
License: LGPLv3
Classifier: Development Status :: 3 - Alpha
Classifier: Environment :: Web Environment
Classifier: Intended Audience :: Developers
Classifier: License :: OSI Approved :: GNU Lesser General Public License v3 (LGPLv3)
Classifier: Operating System :: OS Independent
Classifier: Programming Language :: Python :: 3
Classifier: Programming Language :: Python :: 3.8
Classifier: Programming Language :: Python :: 3.9
Classifier: Programming Language :: Python :: 3.10
Classifier: Programming Language :: Python :: 3.11
Classifier: Programming Language :: Python :: 3.12
Classifier: Programming Language :: Python :: 3.13
Classifier: Programming Language :: Python :: Implementation :: PyPy
Classifier: Topic :: Internet :: WWW/HTTP :: Dynamic Content
Classifier: Topic :: Internet :: WWW/HTTP :: WSGI :: Application
Classifier: Topic :: Software Development :: Libraries :: Application Frameworks
Classifier: Topic :: Software Development :: Libraries :: Python Modules
Requires-Python: >=3
License-File: LICENSE
Requires-Dist: httpx
Requires-Dist: lxml
Requires-Dist: fs
Requires-Dist: Django
Requires-Dist: django-environ
Requires-Dist: pyexcel
Requires-Dist: pyexcel-xlsx
Requires-Dist: pyexcel-ods3
Requires-Dist: xlsxwriter
Requires-Dist: openpyxl
Requires-Dist: python-docx
Requires-Dist: python-dateutil
Requires-Dist: markdown
Requires-Dist: pyquery
Dynamic: author
Dynamic: author-email
Dynamic: classifier
Dynamic: license
Dynamic: license-file
Dynamic: requires-dist
Dynamic: requires-python
Dynamic: summary
